daybook/__init__.py
daybook/__main__.py
daybook/_version.py
daybook/main_settings.yml
daybook/settings.py
daybook/views.py
daybook/adapters/__init__.py
daybook/adapters/repository.py
daybook/domain/__init__.py
daybook/domain/commands.py
daybook/domain/events.py
daybook/domain/model.py
daybook/domain/services.py
daybook/service_layer/__init__.py
daybook/service_layer/daybook.db
daybook/service_layer/handlers.py
daybook/service_layer/messagebus.py
daybook/service_layer/services.py
daybook/service_layer/unit_of_work.py
tests/__init__.py
tests/unit/__init__.py
tests/unit/config.py
tests/unit/test_model.py
tests/unit/test_repository.py
tests/unit/test_services.py
daybook-1.0.4.dist-info/LICENSE
daybook-1.0.4.dist-info/METADATA
daybook-1.0.4.dist-info/WHEEL
daybook-1.0.4.dist-info/entry_points.txt
daybook-1.0.4.dist-info/top_level.txt
daybook-1.0.4.dist-info/RECORD
