Metadata-Version: 2.1
Name: daybook
Version: 1.0.4
Summary: daybook is a reading log cli app
Home-page: https://gitlab.com/miguelamezola/daybook
Author: Miguel Amezola
Author-email: mail@imiguel.net
License: UNKNOWN
Platform: UNKNOWN
Classifier: Programming Language :: Python :: 3
Classifier: License :: OSI Approved :: GNU General Public License v3 (GPLv3)
Classifier: Operating System :: POSIX :: Linux
Classifier: Operating System :: MacOS
Classifier: Intended Audience :: Education
Classifier: Intended Audience :: End Users/Desktop
Requires-Python: >=3.8
Requires-Dist: attrs (==21.4.0)
Requires-Dist: click (==8.0.3)
Requires-Dist: iniconfig (==1.1.1)
Requires-Dist: mypy-extensions (==0.4.3)
Requires-Dist: mysql-connector-python (==8.0.27)
Requires-Dist: mysqlclient (==2.1.0)
Requires-Dist: packaging (==21.3)
Requires-Dist: pathspec (==0.9.0)
Requires-Dist: platformdirs (==2.4.1)
Requires-Dist: pluggy (==1.0.0)
Requires-Dist: protobuf (==3.19.1)
Requires-Dist: py (==1.11.0)
Requires-Dist: pyparsing (==3.0.6)
Requires-Dist: pytest (==6.2.5)
Requires-Dist: pytest-env (==0.6.2)
Requires-Dist: python-dotenv (==0.19.2)
Requires-Dist: PyYAML (==6.0)
Requires-Dist: toml (==0.10.2)
Requires-Dist: tomli (==1.2.3)
Requires-Dist: typing-extensions (==4.0.1)
Requires-Dist: versioneer (==0.21)
